tebless/__init__.py
tebless/devs/__init__.py
tebless/devs/_debug.py
tebless/devs/_widget.py
tebless/devs/decorators.py
tebless/themes/__init__.py
tebless/themes/menu.py
tebless/utils/__init__.py
tebless/utils/keyboard.py
tebless/utils/styles.py
tebless/widgets/__init__.py
tebless/widgets/checkbox.py
tebless/widgets/filter_menu.py
tebless/widgets/input.py
tebless/widgets/label.py
tebless/widgets/menu.py
tebless/widgets/window.py
tebless-1.2.3.dist-info/DESCRIPTION.rst
tebless-1.2.3.dist-info/METADATA
tebless-1.2.3.dist-info/RECORD
tebless-1.2.3.dist-info/WHEEL
tebless-1.2.3.dist-info/dependency_links.txt
tebless-1.2.3.dist-info/metadata.json
tebless-1.2.3.dist-info/top_level.txt
