Metadata-Version: 2.0
Name: tebless
Version: 1.2.3
Summary: This library is a collection of widgets that supported      from blessed allows to create interfaces in a simple way based on events.
Home-page: https://github.com/akhail/tebless
Author: Michel Betancourt
Author-email: MichelBetancourt23@gmail.com
License: MIT license
Keywords: tebless
Platform: UNKNOWN
Classifier: Development Status :: 3 - Alpha
Classifier: Intended Audience :: Developers
Classifier: Environment :: Console :: Curses
Classifier: License :: OSI Approved :: MIT License
Classifier: Natural Language :: English
Classifier: Programming Language :: Python :: 3.5
Classifier: Programming Language :: Python :: 3.6
Requires-Dist: blessed
